{
  "status": "dry_run",
  "generated_at": "2026-05-16T21:06:19.850Z",
  "repo": "openclaw/openclaw",
  "clownfish_repo": "valkyriweb/clownfish",
  "clawsweeper_repo": "openclaw/clawsweeper",
  "since": "2026-05-16T18:05:50.253Z",
  "execute": false,
  "max_comments": 100,
  "max_autoclose_targets": 8,
  "scanned_comments": 100,
  "commands_seen": 12,
  "actionable": 0,
  "trusted_bots": [
    "clawsweeper[bot]",
    "openclaw-clawsweeper[bot]"
  ],
  "allowed_repository_permissions": [
    "admin",
    "maintain",
    "write"
  ],
  "max_auto_repairs_per_head": 1,
  "max_auto_repairs_per_pr": 5,
  "commands": [
    {
      "idempotency_key": "clawsweeper-repair:openclaw/openclaw:82736:4468069061:2026-05-16T20:53:25Z:clawsweeper_auto_repair",
      "comment_id": "4468069061",
      "comment_node_id": "IC_kwDOQb6kR88AAAABClFSxQ",
      "comment_version_key": "4468069061:2026-05-16T20:53:25Z",
      "comment_url": "https://github.com/openclaw/openclaw/pull/82736#issuecomment-4468069061",
      "repo": "openclaw/openclaw",
      "issue_number": 82736,
      "author": "clawsweeper[bot]",
      "author_association": "CONTRIBUTOR",
      "comment_created_at": "2026-05-16T20:47:06Z",
      "comment_updated_at": "2026-05-16T20:53:25Z",
      "trigger": "trusted_bot",
      "command": "clawsweeper auto repair",
      "intent": "clawsweeper_auto_repair",
      "autoclose_message": null,
      "trusted_bot": true,
      "trusted_bot_author": "clawsweeper[bot]",
      "automation_source": "clawsweeper",
      "repair_reason": "structured ClawSweeper verdict: needs-human (sha=2db6e7cbeb8e7070c4d2207b636b31eaaf366c23)",
      "expected_head_sha": "2db6e7cbeb8e7070c4d2207b636b31eaaf366c23",
      "finding_id": null,
      "status": "skipped",
      "actions": [],
      "target": {
        "kind": "pull_request",
        "title": "refactor: unify async media generation",
        "branch": "refactor/async-media-generators",
        "head_sha": "2db6e7cbeb8e7070c4d2207b636b31eaaf366c23",
        "author": "steipete",
        "labels": [
          "docs",
          "agents",
          "maintainer",
          "size: XL",
          "proof: supplied",
          "proof: sufficient"
        ],
        "is_clownfish_pr": false,
        "cluster_id": null,
        "job_path": null,
        "automerge_cluster_id": "automerge-openclaw-openclaw-82736",
        "automerge_job_path": "jobs/openclaw/inbox/automerge-openclaw-openclaw-82736.md",
        "mode": "autonomous",
        "merge_state_status": "CLEAN",
        "review_decision": "",
        "checks": {
          "total": 139,
          "counts": {
            "FAILURE": 3,
            "CANCELLED": 2,
            "SKIPPED": 28,
            "SUCCESS": 105,
            "NEUTRAL": 1
          },
          "blockers": [
            "Real behavior proof:FAILURE",
            "Real behavior proof:FAILURE",
            "Real behavior proof:FAILURE",
            "auto-response:CANCELLED",
            "Real behavior proof:CANCELLED"
          ]
        }
      },
      "reason": "repair commands require a Clownfish PR or a PR opted into Clownfish automerge"
    },
    {
      "idempotency_key": "clawsweeper-repair:openclaw/openclaw:82734:4468049528:2026-05-16T20:45:37Z:clawsweeper_auto_repair",
      "comment_id": "4468049528",
      "comment_node_id": "IC_kwDOQb6kR88AAAABClEGeA",
      "comment_version_key": "4468049528:2026-05-16T20:45:37Z",
      "comment_url": "https://github.com/openclaw/openclaw/pull/82734#issuecomment-4468049528",
      "repo": "openclaw/openclaw",
      "issue_number": 82734,
      "author": "clawsweeper[bot]",
      "author_association": "CONTRIBUTOR",
      "comment_created_at": "2026-05-16T20:41:04Z",
      "comment_updated_at": "2026-05-16T20:45:37Z",
      "trigger": "trusted_bot",
      "command": "clawsweeper auto repair",
      "intent": "clawsweeper_auto_repair",
      "autoclose_message": null,
      "trusted_bot": true,
      "trusted_bot_author": "clawsweeper[bot]",
      "automation_source": "clawsweeper",
      "repair_reason": "structured ClawSweeper verdict: needs-human (sha=9f4183e96a25b7440b0cc78af30109bcbc0bf6d7)",
      "expected_head_sha": "9f4183e96a25b7440b0cc78af30109bcbc0bf6d7",
      "finding_id": null,
      "status": "skipped",
      "actions": [],
      "target": {
        "kind": "pull_request",
        "title": "Bound tool transcript payloads",
        "branch": "fix/bound-tool-transcript-payloads",
        "head_sha": "9f4183e96a25b7440b0cc78af30109bcbc0bf6d7",
        "author": "theemoneytree",
        "labels": [
          "agents",
          "size: S",
          "triage: needs-real-behavior-proof",
          "P2"
        ],
        "is_clownfish_pr": false,
        "cluster_id": null,
        "job_path": null,
        "automerge_cluster_id": "automerge-openclaw-openclaw-82734",
        "automerge_job_path": "jobs/openclaw/inbox/automerge-openclaw-openclaw-82734.md",
        "mode": "autonomous",
        "merge_state_status": "UNSTABLE",
        "review_decision": "",
        "checks": {
          "total": 124,
          "counts": {
            "FAILURE": 6,
            "CANCELLED": 3,
            "SKIPPED": 27,
            "SUCCESS": 87,
            "NEUTRAL": 1
          },
          "blockers": [
            "Real behavior proof:FAILURE",
            "Real behavior proof:FAILURE",
            "Real behavior proof:FAILURE",
            "Real behavior proof:FAILURE",
            "auto-response:CANCELLED",
            "auto-response:CANCELLED",
            "Real behavior proof:CANCELLED",
            "checks-node-agentic-commands-agent-channel:FAILURE",
            "checks-node-core:FAILURE"
          ]
        }
      },
      "reason": "repair commands require a Clownfish PR or a PR opted into Clownfish automerge"
    },
    {
      "idempotency_key": "clawsweeper-repair:openclaw/openclaw:82733:4468043025:2026-05-16T20:54:10Z:clawsweeper_auto_repair",
      "comment_id": "4468043025",
      "comment_node_id": "IC_kwDOQb6kR88AAAABClDtEQ",
      "comment_version_key": "4468043025:2026-05-16T20:54:10Z",
      "comment_url": "https://github.com/openclaw/openclaw/pull/82733#issuecomment-4468043025",
      "repo": "openclaw/openclaw",
      "issue_number": 82733,
      "author": "clawsweeper[bot]",
      "author_association": "CONTRIBUTOR",
      "comment_created_at": "2026-05-16T20:38:36Z",
      "comment_updated_at": "2026-05-16T20:54:10Z",
      "trigger": "trusted_bot",
      "command": "clawsweeper auto repair",
      "intent": "clawsweeper_auto_repair",
      "autoclose_message": null,
      "trusted_bot": true,
      "trusted_bot_author": "clawsweeper[bot]",
      "automation_source": "clawsweeper",
      "repair_reason": "structured ClawSweeper verdict: needs-human (sha=73ff4e2449db4dbe236fbbdee4c89f61167ea3fc)",
      "expected_head_sha": "73ff4e2449db4dbe236fbbdee4c89f61167ea3fc",
      "finding_id": null,
      "status": "skipped",
      "actions": [],
      "target": {
        "kind": "pull_request",
        "title": "fix(diagnostics): recover stale idle embedded-run lanes",
        "branch": "fix/idle-embedded-run-recovery",
        "head_sha": "73ff4e2449db4dbe236fbbdee4c89f61167ea3fc",
        "author": "cavit99",
        "labels": [
          "size: L",
          "proof: supplied",
          "proof: sufficient",
          "P1"
        ],
        "is_clownfish_pr": false,
        "cluster_id": null,
        "job_path": null,
        "automerge_cluster_id": "automerge-openclaw-openclaw-82733",
        "automerge_job_path": "jobs/openclaw/inbox/automerge-openclaw-openclaw-82733.md",
        "mode": "autonomous",
        "merge_state_status": "CLEAN",
        "review_decision": "",
        "checks": {
          "total": 98,
          "counts": {
            "FAILURE": 5,
            "CANCELLED": 8,
            "SKIPPED": 59,
            "SUCCESS": 26
          },
          "blockers": [
            "Real behavior proof:FAILURE",
            "Real behavior proof:FAILURE",
            "Real behavior proof:FAILURE",
            "Real behavior proof:FAILURE",
            "Real behavior proof:FAILURE",
            "auto-response:CANCELLED",
            "auto-response:CANCELLED",
            "auto-response:CANCELLED",
            "auto-response:CANCELLED",
            "auto-response:CANCELLED",
            "Real behavior proof:CANCELLED",
            "Real behavior proof:CANCELLED",
            "Real behavior proof:CANCELLED"
          ]
        }
      },
      "reason": "repair commands require a Clownfish PR or a PR opted into Clownfish automerge"
    },
    {
      "idempotency_key": "clawsweeper-repair:openclaw/openclaw:82731:4468029397:2026-05-16T20:45:50Z:clawsweeper_auto_repair",
      "comment_id": "4468029397",
      "comment_node_id": "IC_kwDOQb6kR88AAAABClC31Q",
      "comment_version_key": "4468029397:2026-05-16T20:45:50Z",
      "comment_url": "https://github.com/openclaw/openclaw/pull/82731#issuecomment-4468029397",
      "repo": "openclaw/openclaw",
      "issue_number": 82731,
      "author": "clawsweeper[bot]",
      "author_association": "CONTRIBUTOR",
      "comment_created_at": "2026-05-16T20:32:33Z",
      "comment_updated_at": "2026-05-16T20:45:50Z",
      "trigger": "trusted_bot",
      "command": "clawsweeper auto repair",
      "intent": "clawsweeper_auto_repair",
      "autoclose_message": null,
      "trusted_bot": true,
      "trusted_bot_author": "clawsweeper[bot]",
      "automation_source": "clawsweeper",
      "repair_reason": "structured ClawSweeper verdict: needs-human (sha=c1e14affa823b986465a0a8d2eb00ce70f1c40ce)",
      "expected_head_sha": "c1e14affa823b986465a0a8d2eb00ce70f1c40ce",
      "finding_id": null,
      "status": "skipped",
      "actions": [],
      "target": {
        "kind": "pull_request",
        "title": "fix(tui): show 0/ctx instead of ?/ctx when usage counters are missing",
        "branch": "fix/tui-footer-token-total",
        "head_sha": "c1e14affa823b986465a0a8d2eb00ce70f1c40ce",
        "author": "leno23",
        "labels": [
          "scripts",
          "size: S",
          "proof: supplied",
          "P2"
        ],
        "is_clownfish_pr": false,
        "cluster_id": null,
        "job_path": null,
        "automerge_cluster_id": "automerge-openclaw-openclaw-82731",
        "automerge_job_path": "jobs/openclaw/inbox/automerge-openclaw-openclaw-82731.md",
        "mode": "autonomous",
        "merge_state_status": "UNSTABLE",
        "review_decision": "",
        "checks": {
          "total": 128,
          "counts": {
            "CANCELLED": 9,
            "SKIPPED": 26,
            "SUCCESS": 90,
            "FAILURE": 2,
            "NEUTRAL": 1
          },
          "blockers": [
            "auto-response:CANCELLED",
            "auto-response:CANCELLED",
            "auto-response:CANCELLED",
            "dispatch:CANCELLED",
            "label:CANCELLED",
            "Real behavior proof:CANCELLED",
            "Real behavior proof:CANCELLED",
            "Real behavior proof:CANCELLED",
            "label-issues:CANCELLED",
            "checks-node-core-runtime-media-ui:FAILURE",
            "checks-node-core:FAILURE"
          ]
        }
      },
      "reason": "repair commands require an open issue or PR"
    },
    {
      "idempotency_key": "clawsweeper-repair:openclaw/openclaw:82730:4468004422:2026-05-16T20:31:32Z:clawsweeper_auto_repair",
      "comment_id": "4468004422",
      "comment_node_id": "IC_kwDOQb6kR88AAAABClBWRg",
      "comment_version_key": "4468004422:2026-05-16T20:31:32Z",
      "comment_url": "https://github.com/openclaw/openclaw/pull/82730#issuecomment-4468004422",
      "repo": "openclaw/openclaw",
      "issue_number": 82730,
      "author": "clawsweeper[bot]",
      "author_association": "CONTRIBUTOR",
      "comment_created_at": "2026-05-16T20:21:41Z",
      "comment_updated_at": "2026-05-16T20:31:32Z",
      "trigger": "trusted_bot",
      "command": "clawsweeper auto repair",
      "intent": "clawsweeper_auto_repair",
      "autoclose_message": null,
      "trusted_bot": true,
      "trusted_bot_author": "clawsweeper[bot]",
      "automation_source": "clawsweeper",
      "repair_reason": "structured ClawSweeper verdict: needs-human (sha=91abde409985d2899be8cd97f4f4a3031ea15ee2)",
      "expected_head_sha": "91abde409985d2899be8cd97f4f4a3031ea15ee2",
      "finding_id": null,
      "status": "skipped",
      "actions": [],
      "target": {
        "kind": "pull_request",
        "title": "feat(slack): add assistant thread lifecycle",
        "branch": "feat/slack-assistant-lifecycle",
        "head_sha": "91abde409985d2899be8cd97f4f4a3031ea15ee2",
        "author": "steipete",
        "labels": [
          "docs",
          "channel: slack",
          "maintainer",
          "size: L",
          "P2"
        ],
        "is_clownfish_pr": false,
        "cluster_id": null,
        "job_path": null,
        "automerge_cluster_id": "automerge-openclaw-openclaw-82730",
        "automerge_job_path": "jobs/openclaw/inbox/automerge-openclaw-openclaw-82730.md",
        "mode": "autonomous",
        "merge_state_status": "CLEAN",
        "review_decision": "",
        "checks": {
          "total": 124,
          "counts": {
            "FAILURE": 2,
            "CANCELLED": 1,
            "SKIPPED": 25,
            "SUCCESS": 95,
            "NEUTRAL": 1
          },
          "blockers": [
            "Real behavior proof:FAILURE",
            "Real behavior proof:FAILURE",
            "auto-response:CANCELLED"
          ]
        }
      },
      "reason": "repair commands require a Clownfish PR or a PR opted into Clownfish automerge"
    },
    {
      "idempotency_key": "clawsweeper-repair:openclaw/openclaw:82727:4467989075:2026-05-16T20:56:28Z:clawsweeper_auto_repair",
      "comment_id": "4467989075",
      "comment_node_id": "IC_kwDOQb6kR88AAAABClAaUw",
      "comment_version_key": "4467989075:2026-05-16T20:56:28Z",
      "comment_url": "https://github.com/openclaw/openclaw/pull/82727#issuecomment-4467989075",
      "repo": "openclaw/openclaw",
      "issue_number": 82727,
      "author": "clawsweeper[bot]",
      "author_association": "CONTRIBUTOR",
      "comment_created_at": "2026-05-16T20:14:45Z",
      "comment_updated_at": "2026-05-16T20:56:28Z",
      "trigger": "trusted_bot",
      "command": "clawsweeper auto repair",
      "intent": "clawsweeper_auto_repair",
      "autoclose_message": null,
      "trusted_bot": true,
      "trusted_bot_author": "clawsweeper[bot]",
      "automation_source": "clawsweeper",
      "repair_reason": "structured ClawSweeper verdict: needs-human (sha=228e33b8bd6cda4b108fd7ea256e85f25e7eafd2)",
      "expected_head_sha": "228e33b8bd6cda4b108fd7ea256e85f25e7eafd2",
      "finding_id": null,
      "status": "skipped",
      "actions": [],
      "target": {
        "kind": "pull_request",
        "title": "fix(tailscale): retry status --json after transient startup failures",
        "branch": "fix/tailscale-status-json-retry",
        "head_sha": "228e33b8bd6cda4b108fd7ea256e85f25e7eafd2",
        "author": "leno23",
        "labels": [
          "scripts",
          "size: S",
          "proof: supplied",
          "P2"
        ],
        "is_clownfish_pr": false,
        "cluster_id": null,
        "job_path": null,
        "automerge_cluster_id": "automerge-openclaw-openclaw-82727",
        "automerge_job_path": "jobs/openclaw/inbox/automerge-openclaw-openclaw-82727.md",
        "mode": "autonomous",
        "merge_state_status": "CLEAN",
        "review_decision": "",
        "checks": {
          "total": 113,
          "counts": {
            "SUCCESS": 90,
            "SKIPPED": 22,
            "NEUTRAL": 1
          },
          "blockers": []
        }
      },
      "reason": "repair commands require a Clownfish PR or a PR opted into Clownfish automerge"
    },
    {
      "idempotency_key": "clawsweeper-repair:openclaw/openclaw:82725:4467967341:2026-05-16T20:09:19Z:clawsweeper_auto_repair",
      "comment_id": "4467967341",
      "comment_node_id": "IC_kwDOQb6kR88AAAABCk_FbQ",
      "comment_version_key": "4467967341:2026-05-16T20:09:19Z",
      "comment_url": "https://github.com/openclaw/openclaw/pull/82725#issuecomment-4467967341",
      "repo": "openclaw/openclaw",
      "issue_number": 82725,
      "author": "clawsweeper[bot]",
      "author_association": "CONTRIBUTOR",
      "comment_created_at": "2026-05-16T20:04:48Z",
      "comment_updated_at": "2026-05-16T20:09:19Z",
      "trigger": "trusted_bot",
      "command": "clawsweeper auto repair",
      "intent": "clawsweeper_auto_repair",
      "autoclose_message": null,
      "trusted_bot": true,
      "trusted_bot_author": "clawsweeper[bot]",
      "automation_source": "clawsweeper",
      "repair_reason": "structured ClawSweeper verdict: needs-human (sha=ef261bbb77e2b5e96d0ffce9a88e322390b2b262)",
      "expected_head_sha": "ef261bbb77e2b5e96d0ffce9a88e322390b2b262",
      "finding_id": null,
      "status": "skipped",
      "actions": [],
      "target": {
        "kind": "pull_request",
        "title": "Log Codex OAuth refresh diagnostics",
        "branch": "codex-oauth-refresh-diagnostic",
        "head_sha": "ef261bbb77e2b5e96d0ffce9a88e322390b2b262",
        "author": "shravansunder",
        "labels": [
          "size: S",
          "extensions: codex",
          "triage: needs-real-behavior-proof",
          "P2"
        ],
        "is_clownfish_pr": false,
        "cluster_id": null,
        "job_path": null,
        "automerge_cluster_id": "automerge-openclaw-openclaw-82725",
        "automerge_job_path": "jobs/openclaw/inbox/automerge-openclaw-openclaw-82725.md",
        "mode": "autonomous",
        "merge_state_status": "UNSTABLE",
        "review_decision": "",
        "checks": {
          "total": 118,
          "counts": {
            "FAILURE": 5,
            "CANCELLED": 4,
            "SKIPPED": 27,
            "SUCCESS": 81,
            "NEUTRAL": 1
          },
          "blockers": [
            "Real behavior proof:FAILURE",
            "Real behavior proof:FAILURE",
            "Real behavior proof:FAILURE",
            "auto-response:CANCELLED",
            "auto-response:CANCELLED",
            "Real behavior proof:CANCELLED",
            "Real behavior proof:CANCELLED",
            "checks-node-agentic-commands-agent-channel:FAILURE",
            "checks-node-core:FAILURE"
          ]
        }
      },
      "reason": "repair commands require a Clownfish PR or a PR opted into Clownfish automerge"
    },
    {
      "idempotency_key": "clawsweeper-repair:openclaw/openclaw:82724:4467958166:2026-05-16T20:37:57Z:clawsweeper_auto_repair",
      "comment_id": "4467958166",
      "comment_node_id": "IC_kwDOQb6kR88AAAABCk-hlg",
      "comment_version_key": "4467958166:2026-05-16T20:37:57Z",
      "comment_url": "https://github.com/openclaw/openclaw/pull/82724#issuecomment-4467958166",
      "repo": "openclaw/openclaw",
      "issue_number": 82724,
      "author": "clawsweeper[bot]",
      "author_association": "CONTRIBUTOR",
      "comment_created_at": "2026-05-16T20:00:45Z",
      "comment_updated_at": "2026-05-16T20:37:57Z",
      "trigger": "trusted_bot",
      "command": "clawsweeper auto repair",
      "intent": "clawsweeper_auto_repair",
      "autoclose_message": null,
      "trusted_bot": true,
      "trusted_bot_author": "clawsweeper[bot]",
      "automation_source": "clawsweeper",
      "repair_reason": "structured ClawSweeper verdict: needs-human (sha=e2ad6c7d83cbd17cbfbe0cfca90223f2b3b43f6a)",
      "expected_head_sha": "e2ad6c7d83cbd17cbfbe0cfca90223f2b3b43f6a",
      "finding_id": null,
      "status": "skipped",
      "actions": [],
      "target": {
        "kind": "pull_request",
        "title": "fix(subagents): make completion handoff review-first",
        "branch": "codex/subagent-review-handoff",
        "head_sha": "e2ad6c7d83cbd17cbfbe0cfca90223f2b3b43f6a",
        "author": "100menotu001",
        "labels": [
          "docs",
          "agents",
          "size: XS",
          "proof: supplied",
          "proof: sufficient",
          "P2"
        ],
        "is_clownfish_pr": false,
        "cluster_id": null,
        "job_path": null,
        "automerge_cluster_id": "automerge-openclaw-openclaw-82724",
        "automerge_job_path": "jobs/openclaw/inbox/automerge-openclaw-openclaw-82724.md",
        "mode": "autonomous",
        "merge_state_status": "CLEAN",
        "review_decision": "",
        "checks": {
          "total": 115,
          "counts": {
            "CANCELLED": 3,
            "SUCCESS": 89,
            "SKIPPED": 22,
            "NEUTRAL": 1
          },
          "blockers": [
            "auto-response:CANCELLED",
            "dispatch:CANCELLED",
            "Real behavior proof:CANCELLED"
          ]
        }
      },
      "reason": "repair commands require a Clownfish PR or a PR opted into Clownfish automerge"
    },
    {
      "idempotency_key": "clawsweeper-repair:openclaw/openclaw:82723:4467957563:2026-05-16T20:45:07Z:clawsweeper_auto_repair",
      "comment_id": "4467957563",
      "comment_node_id": "IC_kwDOQb6kR88AAAABCk-fOw",
      "comment_version_key": "4467957563:2026-05-16T20:45:07Z",
      "comment_url": "https://github.com/openclaw/openclaw/pull/82723#issuecomment-4467957563",
      "repo": "openclaw/openclaw",
      "issue_number": 82723,
      "author": "clawsweeper[bot]",
      "author_association": "CONTRIBUTOR",
      "comment_created_at": "2026-05-16T20:00:28Z",
      "comment_updated_at": "2026-05-16T20:45:07Z",
      "trigger": "trusted_bot",
      "command": "clawsweeper auto repair",
      "intent": "clawsweeper_auto_repair",
      "autoclose_message": null,
      "trusted_bot": true,
      "trusted_bot_author": "clawsweeper[bot]",
      "automation_source": "clawsweeper",
      "repair_reason": "structured ClawSweeper verdict: needs-human (sha=2b2f668b2134ed40667025feee02583667f123f7)",
      "expected_head_sha": "2b2f668b2134ed40667025feee02583667f123f7",
      "finding_id": null,
      "status": "skipped",
      "actions": [],
      "target": {
        "kind": "pull_request",
        "title": "docs: add config unset dry-run documentation",
        "branch": "docs/config-unset-dry-run",
        "head_sha": "2b2f668b2134ed40667025feee02583667f123f7",
        "author": "enjouzeratul",
        "labels": [
          "docs",
          "size: XS",
          "triage: needs-real-behavior-proof",
          "P3"
        ],
        "is_clownfish_pr": false,
        "cluster_id": null,
        "job_path": null,
        "automerge_cluster_id": "automerge-openclaw-openclaw-82723",
        "automerge_job_path": "jobs/openclaw/inbox/automerge-openclaw-openclaw-82723.md",
        "mode": "autonomous",
        "merge_state_status": "UNSTABLE",
        "review_decision": "",
        "checks": {
          "total": 88,
          "counts": {
            "FAILURE": 1,
            "SUCCESS": 79,
            "SKIPPED": 8
          },
          "blockers": [
            "Real behavior proof:FAILURE"
          ]
        }
      },
      "reason": "repair commands require a Clownfish PR or a PR opted into Clownfish automerge"
    },
    {
      "idempotency_key": "clawsweeper-repair:openclaw/openclaw:82722:4467945170:2026-05-16T19:59:59Z:clawsweeper_auto_repair",
      "comment_id": "4467945170",
      "comment_node_id": "IC_kwDOQb6kR88AAAABCk9u0g",
      "comment_version_key": "4467945170:2026-05-16T19:59:59Z",
      "comment_url": "https://github.com/openclaw/openclaw/issues/82722#issuecomment-4467945170",
      "repo": "openclaw/openclaw",
      "issue_number": 82722,
      "author": "clawsweeper[bot]",
      "author_association": "CONTRIBUTOR",
      "comment_created_at": "2026-05-16T19:54:13Z",
      "comment_updated_at": "2026-05-16T19:59:59Z",
      "trigger": "trusted_bot",
      "command": "clawsweeper auto repair",
      "intent": "clawsweeper_auto_repair",
      "autoclose_message": null,
      "trusted_bot": true,
      "trusted_bot_author": "clawsweeper[bot]",
      "automation_source": "clawsweeper",
      "repair_reason": "ClawSweeper review comment asks to keep repairing this PR",
      "expected_head_sha": null,
      "finding_id": null,
      "status": "skipped",
      "actions": [],
      "target": {
        "kind": "issue",
        "state": "open",
        "title": "Heartbeat polls still interrupt model responses during streaming (not just tool calls)",
        "labels": [
          "P1",
          "clawsweeper:needs-live-repro"
        ]
      },
      "reason": "repair commands require a pull request"
    },
    {
      "idempotency_key": "clawsweeper-repair:openclaw/openclaw:82721:4467933672:2026-05-16T20:17:56Z:clawsweeper_auto_repair",
      "comment_id": "4467933672",
      "comment_node_id": "IC_kwDOQb6kR88AAAABCk9B6A",
      "comment_version_key": "4467933672:2026-05-16T20:17:56Z",
      "comment_url": "https://github.com/openclaw/openclaw/pull/82721#issuecomment-4467933672",
      "repo": "openclaw/openclaw",
      "issue_number": 82721,
      "author": "clawsweeper[bot]",
      "author_association": "CONTRIBUTOR",
      "comment_created_at": "2026-05-16T19:49:00Z",
      "comment_updated_at": "2026-05-16T20:17:56Z",
      "trigger": "trusted_bot",
      "command": "clawsweeper auto repair",
      "intent": "clawsweeper_auto_repair",
      "autoclose_message": null,
      "trusted_bot": true,
      "trusted_bot_author": "clawsweeper[bot]",
      "automation_source": "clawsweeper",
      "repair_reason": "structured ClawSweeper verdict: needs-human (sha=615cfbef1c078f8b5421adccb47ee47e6cfc5b38)",
      "expected_head_sha": "615cfbef1c078f8b5421adccb47ee47e6cfc5b38",
      "finding_id": null,
      "status": "skipped",
      "actions": [],
      "target": {
        "kind": "pull_request",
        "title": "fix(launcher): avoid redundant compile-cache respawn on each CLI run",
        "branch": "fix/compile-cache-root-comparison",
        "head_sha": "615cfbef1c078f8b5421adccb47ee47e6cfc5b38",
        "author": "leno23",
        "labels": [
          "scripts",
          "size: S",
          "proof: supplied",
          "proof: sufficient",
          "P2"
        ],
        "is_clownfish_pr": false,
        "cluster_id": null,
        "job_path": null,
        "automerge_cluster_id": "automerge-openclaw-openclaw-82721",
        "automerge_job_path": "jobs/openclaw/inbox/automerge-openclaw-openclaw-82721.md",
        "mode": "autonomous",
        "merge_state_status": "CLEAN",
        "review_decision": "",
        "checks": {
          "total": 93,
          "counts": {
            "SKIPPED": 9,
            "SUCCESS": 84
          },
          "blockers": []
        }
      },
      "reason": "repair commands require a Clownfish PR or a PR opted into Clownfish automerge"
    },
    {
      "idempotency_key": "clawsweeper-repair:openclaw/openclaw:82720:4467921628:2026-05-16T19:48:10Z:clawsweeper_auto_repair",
      "comment_id": "4467921628",
      "comment_node_id": "IC_kwDOQb6kR88AAAABCk8S3A",
      "comment_version_key": "4467921628:2026-05-16T19:48:10Z",
      "comment_url": "https://github.com/openclaw/openclaw/pull/82720#issuecomment-4467921628",
      "repo": "openclaw/openclaw",
      "issue_number": 82720,
      "author": "clawsweeper[bot]",
      "author_association": "CONTRIBUTOR",
      "comment_created_at": "2026-05-16T19:43:28Z",
      "comment_updated_at": "2026-05-16T19:48:10Z",
      "trigger": "trusted_bot",
      "command": "clawsweeper auto repair",
      "intent": "clawsweeper_auto_repair",
      "autoclose_message": null,
      "trusted_bot": true,
      "trusted_bot_author": "clawsweeper[bot]",
      "automation_source": "clawsweeper",
      "repair_reason": "structured ClawSweeper verdict: needs-human (sha=624e4cc91cc9a011c15ec16dd014dc6a3daa4dad)",
      "expected_head_sha": "624e4cc91cc9a011c15ec16dd014dc6a3daa4dad",
      "finding_id": null,
      "status": "skipped",
      "actions": [],
      "target": {
        "kind": "pull_request",
        "title": "fix(tasks): fail closed stale cli owner main sessions",
        "branch": "codex/fix-stale-cli-owner-main-session",
        "head_sha": "624e4cc91cc9a011c15ec16dd014dc6a3daa4dad",
        "author": "jaddahelpifyr",
        "labels": [
          "docs",
          "size: S",
          "triage: needs-real-behavior-proof",
          "P3"
        ],
        "is_clownfish_pr": false,
        "cluster_id": null,
        "job_path": null,
        "automerge_cluster_id": "automerge-openclaw-openclaw-82720",
        "automerge_job_path": "jobs/openclaw/inbox/automerge-openclaw-openclaw-82720.md",
        "mode": "autonomous",
        "merge_state_status": "UNSTABLE",
        "review_decision": "",
        "checks": {
          "total": 124,
          "counts": {
            "FAILURE": 9,
            "CANCELLED": 2,
            "SKIPPED": 26,
            "SUCCESS": 86,
            "NEUTRAL": 1
          },
          "blockers": [
            "Real behavior proof:FAILURE",
            "Real behavior proof:FAILURE",
            "Real behavior proof:FAILURE",
            "Real behavior proof:FAILURE",
            "auto-response:CANCELLED",
            "Real behavior proof:CANCELLED",
            "check-lint:FAILURE",
            "check-additional-boundaries-b:FAILURE",
            "check-additional-extension-bundled:FAILURE",
            "check:FAILURE",
            "check-additional:FAILURE"
          ]
        }
      },
      "reason": "repair commands require an open issue or PR"
    }
  ]
}
